minerva/__init__.py
minerva/error.py
minerva/commands/__init__.py
minerva/commands/aggregation.py
minerva/commands/alias.py
minerva/commands/attribute_store.py
minerva/commands/data_source.py
minerva/commands/entity_type.py
minerva/commands/generate_sample_data.py
minerva/commands/initialize.py
minerva/commands/live_monitor.py
minerva/commands/load_data.py
minerva/commands/load_sample_data.py
minerva/commands/minerva_cli.py
minerva/commands/notification_store.py
minerva/commands/partition.py
minerva/commands/quick_start.py
minerva/commands/relation.py
minerva/commands/report.py
minerva/commands/structure.py
minerva/commands/trend_materialization.py
minerva/commands/trend_store.py
minerva/commands/trigger.py
minerva/commands/virtual_entity.py
minerva/db/__init__.py
minerva/db/error.py
minerva/db/generic.py
minerva/db/postgresql.py
minerva/db/query.py
minerva/db/util.py
minerva/directory/__init__.py
minerva/directory/alias.py
minerva/directory/basetypes.py
minerva/directory/datasource.py
minerva/directory/distinguishedname.py
minerva/directory/entity.py
minerva/directory/entityref.py
minerva/directory/entitytype.py
minerva/directory/existence.py
minerva/directory/helpers.py
minerva/directory/minervaexception.py
minerva/directory/query.py
minerva/directory/query_types.py
minerva/directory/relationtype.py
minerva/directory/tag.py
minerva/directory/taggroup.py
minerva/harvest/__init__.py
minerva/harvest/error.py
minerva/harvest/fileprocessor.py
minerva/harvest/plugin_api_attribute.py
minerva/harvest/plugin_api_trend.py
minerva/harvest/plugins.py
minerva/harvest/trend_config_deducer.py
minerva/instance/__init__.py
minerva/instance/aggregation_compilation.py
minerva/instance/aggregation_generation.py
minerva/instance/generating.py
minerva/instance/resources/Makefile
minerva/instance/resources/requirements.txt
minerva/instance/resources/attribute/README.md
minerva/instance/resources/bin/activate
minerva/instance/resources/custom/post-init/README.md
minerva_etl-5.3.2.dist-info/COPYING
minerva_etl-5.3.2.dist-info/METADATA
minerva_etl-5.3.2.dist-info/WHEEL
minerva_etl-5.3.2.dist-info/entry_points.txt
minerva_etl-5.3.2.dist-info/top_level.txt
minerva_etl-5.3.2.dist-info/RECORD
