Metadata-Version: 2.1
Name: minerva-etl
Version: 5.3.2
Summary: UNKNOWN
Home-page: UNKNOWN
Author: Hendrikx ITC
Author-email: info@hendrikx-itc.nl
License: GPL
Platform: UNKNOWN
Requires-Python: >3.6
Requires-Dist: PyYAML
Requires-Dist: configobj
Requires-Dist: jinja2
Requires-Dist: psycopg2 (>=2.8)
Requires-Dist: pyparsing
Requires-Dist: python-dateutil
Requires-Dist: pytz
Provides-Extra: tests
Requires-Dist: docker ; extra == 'tests'
Requires-Dist: pytest ; extra == 'tests'
